unicode_rbnf/__init__.py
unicode_rbnf/__main__.py
unicode_rbnf/decimal_format.py
unicode_rbnf/engine.py
unicode_rbnf/py.typed
unicode_rbnf/rbnf/af.xml
unicode_rbnf/rbnf/ak.xml
unicode_rbnf/rbnf/am.xml
unicode_rbnf/rbnf/ar.xml
unicode_rbnf/rbnf/az.xml
unicode_rbnf/rbnf/be.xml
unicode_rbnf/rbnf/bg.xml
unicode_rbnf/rbnf/bs.xml
unicode_rbnf/rbnf/ca.xml
unicode_rbnf/rbnf/ccp.xml
unicode_rbnf/rbnf/chr.xml
unicode_rbnf/rbnf/cs.xml
unicode_rbnf/rbnf/cy.xml
unicode_rbnf/rbnf/da.xml
unicode_rbnf/rbnf/de.xml
unicode_rbnf/rbnf/de_CH.xml
unicode_rbnf/rbnf/ee.xml
unicode_rbnf/rbnf/el.xml
unicode_rbnf/rbnf/en.xml
unicode_rbnf/rbnf/en_IN.xml
unicode_rbnf/rbnf/eo.xml
unicode_rbnf/rbnf/es.xml
unicode_rbnf/rbnf/et.xml
unicode_rbnf/rbnf/fa.xml
unicode_rbnf/rbnf/fa_AF.xml
unicode_rbnf/rbnf/ff.xml
unicode_rbnf/rbnf/fi.xml
unicode_rbnf/rbnf/fil.xml
unicode_rbnf/rbnf/fo.xml
unicode_rbnf/rbnf/fr.xml
unicode_rbnf/rbnf/fr_BE.xml
unicode_rbnf/rbnf/fr_CH.xml
unicode_rbnf/rbnf/ga.xml
unicode_rbnf/rbnf/he.xml
unicode_rbnf/rbnf/hi.xml
unicode_rbnf/rbnf/hr.xml
unicode_rbnf/rbnf/hu.xml
unicode_rbnf/rbnf/hy.xml
unicode_rbnf/rbnf/id.xml
unicode_rbnf/rbnf/is.xml
unicode_rbnf/rbnf/it.xml
unicode_rbnf/rbnf/ja.xml
unicode_rbnf/rbnf/ka.xml
unicode_rbnf/rbnf/kk.xml
unicode_rbnf/rbnf/kl.xml
unicode_rbnf/rbnf/km.xml
unicode_rbnf/rbnf/ko.xml
unicode_rbnf/rbnf/ky.xml
unicode_rbnf/rbnf/lb.xml
unicode_rbnf/rbnf/lo.xml
unicode_rbnf/rbnf/lrc.xml
unicode_rbnf/rbnf/lt.xml
unicode_rbnf/rbnf/lv.xml
unicode_rbnf/rbnf/mk.xml
unicode_rbnf/rbnf/ms.xml
unicode_rbnf/rbnf/mt.xml
unicode_rbnf/rbnf/my.xml
unicode_rbnf/rbnf/ne.xml
unicode_rbnf/rbnf/nl.xml
unicode_rbnf/rbnf/nn.xml
unicode_rbnf/rbnf/no.xml
unicode_rbnf/rbnf/pl.xml
unicode_rbnf/rbnf/pt.xml
unicode_rbnf/rbnf/pt_PT.xml
unicode_rbnf/rbnf/qu.xml
unicode_rbnf/rbnf/ro.xml
unicode_rbnf/rbnf/ru.xml
unicode_rbnf/rbnf/se.xml
unicode_rbnf/rbnf/sk.xml
unicode_rbnf/rbnf/sl.xml
unicode_rbnf/rbnf/sq.xml
unicode_rbnf/rbnf/sr.xml
unicode_rbnf/rbnf/sr_Latn.xml
unicode_rbnf-2.2.0.dist-info/LICENSE.md
unicode_rbnf-2.2.0.dist-info/METADATA
unicode_rbnf-2.2.0.dist-info/WHEEL
unicode_rbnf-2.2.0.dist-info/top_level.txt
unicode_rbnf-2.2.0.dist-info/zip-safe
unicode_rbnf-2.2.0.dist-info/RECORD
