Metadata-Version: 2.1
Name: unicode-rbnf
Version: 2.2.0
Summary: Rule-based number formatting using Unicode CLDR data
Author-email: Michael Hansen <mike@rhasspy.org>
License: MIT
Project-URL: Source Code, https://github.com/rhasspy/unicode-rbnf
Keywords: rbnf,unicode,number,format
Platform: any
Classifier: Development Status :: 3 - Alpha
Classifier: Intended Audience :: Developers
Classifier: Topic :: Text Processing :: Linguistic
Classifier: License :: OSI Approved :: MIT License
Classifier: Programming Language :: Python :: 3.8
Classifier: Programming Language :: Python :: 3.9
Classifier: Programming Language :: Python :: 3.10
Classifier: Programming Language :: Python :: 3.11
Classifier: Programming Language :: Python :: 3.12
Classifier: Programming Language :: Python :: 3.13
Requires-Python: >=3.8.0
License-File: LICENSE.md
